analysis/__init__.py
analysis/main.py
analysis/strings.exe
analysis/trid.exe
bin/strings.exe
static_analysis_script-0.2.7.dist-info/METADATA
static_analysis_script-0.2.7.dist-info/WHEEL
static_analysis_script-0.2.7.dist-info/entry_points.txt
static_analysis_script-0.2.7.dist-info/top_level.txt
static_analysis_script-0.2.7.dist-info/RECORD
