Metadata-Version: 2.1
Name: static-analysis-script
Version: 0.2.7
Summary: A utility to perform static analysis on files.
Home-page: https://github.com/perzibel/static-analysis-script
Author: Perzibel
Author-email: perzibel@outlook.com
Classifier: Development Status :: 3 - Alpha
Classifier: Intended Audience :: Information Technology
Classifier: Topic :: Security
Classifier: License :: OSI Approved :: MIT License
Classifier: Programming Language :: Python :: 3
Classifier: Programming Language :: Python :: 3.7
Classifier: Programming Language :: Python :: 3.8
Classifier: Programming Language :: Python :: 3.9
Requires-Dist: PyPDF2
Requires-Dist: tqdm
Requires-Dist: numpy
Requires-Dist: pyfiglet
Requires-Dist: colorama
Requires-Dist: setuptools-scm
